MANIFEST.in
README.rst
setup.py
we_get/__init__.py
we_get/__main__.py
we_get.egg-info/PKG-INFO
we_get.egg-info/SOURCES.txt
we_get.egg-info/dependency_links.txt
we_get.egg-info/entry_points.txt
we_get.egg-info/requires.txt
we_get.egg-info/top_level.txt
we_get/core/__init__.py
we_get/core/commands.py
we_get/core/completer.py
we_get/core/module.py
we_get/core/shell.py
we_get/core/stack.py
we_get/core/style.py
we_get/core/tests.py
we_get/core/utils.py
we_get/core/we_get.py
we_get/extra/useragents.txt
we_get/modules/1337x.py
we_get/modules/__init__.py
we_get/modules/eztv.py
we_get/modules/the_pirate_bay.py
we_get/modules/yts.py